wanderer/__init__.py
wanderer/admin.py
wanderer/apps.py
wanderer/auth_hooks.py
wanderer/managers.py
wanderer/models.py
wanderer/tasks.py
wanderer/urls.py
wanderer/views.py
wanderer/wanderer.py
wanderer/locale/en/LC_MESSAGES/django.po
wanderer/management/commands/wanderer_cleanup_acls.py
wanderer/migrations/0001_initial.py
wanderer/migrations/__init__.py
wanderer/templates/wanderer/wmm_services_ctrl.html
wanderer/tests/__init__.py
wanderer/tests/test_api.py
wanderer/tests/test_map.py
wanderer/tests/test_tasks.py
wanderer/tests/utils.py
aa_wanderer-0.1.5.dist-info/licenses/LICENSE
aa_wanderer-0.1.5.dist-info/WHEEL
aa_wanderer-0.1.5.dist-info/METADATA
aa_wanderer-0.1.5.dist-info/RECORD
