Metadata-Version: 2.4
Name: aa-wanderer
Version: 0.1.5
Summary: AA wanderer
Author-email: T'rahk Rokym <trahk.rokym@gmail.com>
Requires-Python: >=3.10
Classifier: Environment :: Web Environment
Classifier: Framework :: Django
Classifier: Framework :: Django :: 4.2
Classifier: Intended Audience :: Developers
Classifier: License :: OSI Approved :: MIT License
Classifier: Operating System :: OS Independent
Classifier: Programming Language :: Python
Classifier: Programming Language :: Python :: 3.10
Classifier: Programming Language :: Python :: 3.11
Classifier: Programming Language :: Python :: 3.12
Classifier: Programming Language :: Python :: 3.13
Classifier: Topic :: Internet :: WWW/HTTP
Classifier: Topic :: Internet :: WWW/HTTP :: Dynamic Content
License-File: LICENSE
Requires-Dist: allianceauth>=4
Requires-Dist: allianceauth-app-utils>=1.25
Project-URL: Changelog, https://gitlab.com/r0kym/aa-wanderer/-/blob/master/CHANGELOG.md
Project-URL: Homepage, https://gitlab.com/r0kym/aa-wanderer
Project-URL: Source, https://gitlab.com/r0kym/aa-wanderer
Project-URL: Tracker, https://gitlab.com/r0kym/aa-wanderer/-/issues
